<?xml version="1.0" encoding="UTF-8" standalone="no"?>
<game game-type="season" uuid="b0772ddc687d4814a640d9726387364a" version="2.1">
  <meta>
    <homeTeam>
      <team defStrat="MAN" discordId="592213329204871170" fullName="Seminoles" id="floridast" offStrat="5-Out" shortName="Florida State"/>
    </homeTeam>
    <awayTeam>
      <team defStrat="MAN" discordId="341365184021004290" fullName="Hurricanes" id="miamifl" offStrat="ISO" shortName="Miami (FL)"/>
    </awayTeam>
    <startTime>1615051722268</startTime>
    <gameTitle>Week Ten (ACC)</gameTitle>
    <channelName>fsu-vs-mia</channelName>
  </meta>
  <scores>
    <quarter away="59" home="68" q="F"/>
    <quarter away="13" home="12" q="1"/>
    <quarter away="19" home="16" q="2"/>
    <quarter away="15" home="19" q="3"/>
    <quarter away="12" home="21" q="4"/>
    <quarter away="0" home="0" q="O1"/>
  </scores>
  <plays>
    <tipoff away="420" home="920" tip="405"/>
    <play numDef="789" numOff="222" pos="away" pts="3" q="1" result="turnover"/>
    <play numDef="999" numOff="550" pos="home" pts="2" q="1" result="turnover"/>
    <play numDef="690" numOff="199" pos="away" pts="3" q="1" result="dunk"/>
    <play numDef="678" numOff="707" pos="away" pts="3" q="1" result="made"/>
    <play numDef="411" numOff="250" pos="home" pts="2" q="1" result="made"/>
    <play numDef="920" numOff="904" pos="away" pts="3" q="1" result="and1"/>
    <playFT numDef="1000" numOff="250" pos="away" q="1" throws="1" throwsMade="1"/>
    <play numDef="101" numOff="444" pos="home" pts="3" q="1" result="miss"/>
    <play numDef="69" numOff="500" pos="away" pts="3" q="1" result="turnover"/>
    <play numDef="69" numOff="222" pos="home" pts="2" q="1" result="made"/>
    <play numDef="710" numOff="399" pos="away" pts="3" q="1" result="miss"/>
    <play numDef="311" numOff="844" pos="home" pts="2" q="1" result="turnover"/>
    <play numDef="166" numOff="404" pos="away" pts="3" q="1" result="rebound"/>
    <play numDef="375" numOff="711" pos="away" pts="3" q="1" result="miss"/>
    <play numDef="750" numOff="888" pos="home" pts="2" q="1" result="made"/>
    <play numDef="828" numOff="199" pos="away" pts="3" q="1" result="miss"/>
    <play numDef="828" numOff="750" pos="home" pts="2" q="1" result="made"/>
    <play numDef="666" numOff="333" pos="away" pts="3" q="1" result="miss"/>
    <play numDef="333" numOff="110" pos="home" pts="2" q="1" result="made"/>
    <play numDef="920" numOff="750" pos="away" pts="3" q="1" result="made"/>
    <play numDef="900" numOff="300" pos="home" pts="3" q="1" result="turnover"/>
    <play numDef="800" numOff="599" pos="away" pts="3" q="1" result="made"/>
    <play numDef="1" numOff="420" pos="home" pts="2" q="2" result="miss"/>
    <play numDef="420" numOff="399" pos="away" pts="3" q="2" result="made"/>
    <play numDef="20" numOff="69" pos="home" pts="3" q="2" result="made"/>
    <play numDef="569" numOff="811" pos="away" pts="3" q="2" result="rebound"/>
    <play numDef="666" numOff="669" pos="away" pts="3" q="2" result="and1"/>
    <playFT numDef="666" numOff="750" pos="away" q="2" throws="1" throwsMade="1"/>
    <play numDef="166" numOff="920" pos="home" pts="3" q="2" result="miss"/>
    <play numDef="45" numOff="888" pos="away" pts="3" q="2" result="made"/>
    <play numDef="420" numOff="731" pos="home" pts="2" q="2" result="foul"/>
    <playFT numDef="111" numOff="500" pos="home" q="2" throws="2" throwsMade="1"/>
    <play numDef="250" numOff="904" pos="away" pts="3" q="2" result="miss"/>
    <play numDef="222" numOff="303" pos="home" pts="2" q="2" result="made"/>
    <play numDef="200" numOff="404" pos="away" pts="3" q="2" result="made"/>
    <play numDef="66" numOff="678" pos="home" pts="2" q="2" result="miss"/>
    <play numDef="678" numOff="199" pos="away" pts="3" q="2" result="dunk"/>
    <play numDef="678" numOff="500" pos="away" pts="3" q="2" result="made"/>
    <play numDef="345" numOff="900" offStrat="hurry" pos="home" pts="3" q="2" result="turnover"/>
    <play numDef="845" numOff="222" pos="away" pts="3" q="2" result="miss"/>
    <play numDef="111" numOff="100" offStrat="hurry" pos="home" pts="3" q="2" result="and1"/>
    <playFT numDef="500" numOff="500" pos="home" q="2" throws="1" throwsMade="1"/>
    <play numDef="234" numOff="750" pos="away" pts="3" q="2" result="dunk"/>
    <play numDef="375" numOff="199" pos="away" pts="3" q="2" result="made"/>
    <play numDef="699" numOff="789" pos="home" pts="2" q="2" result="made"/>
    <play numDef="777" numOff="1000" pos="home" pts="3" q="3" result="rebound"/>
    <play numDef="904" numOff="1000" pos="home" pts="3" q="3" result="made"/>
    <play numDef="166" numOff="299" pos="away" pts="3" q="3" result="made"/>
    <play numDef="33" numOff="329" pos="home" pts="2" q="3" result="made"/>
    <play numDef="199" numOff="555" pos="away" pts="3" q="3" result="miss"/>
    <play numDef="911" numOff="920" pos="home" pts="2" q="3" result="and1"/>
    <playFT numDef="1" numOff="175" pos="home" q="3" throws="1" throwsMade="1"/>
    <play numDef="860" numOff="711" pos="away" pts="3" q="3" result="made"/>
    <play numDef="811" numOff="1" pos="home" pts="2" q="3" result="made"/>
    <play numDef="555" numOff="904" pos="away" pts="3" q="3" result="miss"/>
    <play numDef="500" numOff="404" pos="home" pts="2" q="3" result="made"/>
    <play numDef="700" numOff="717" pos="away" pts="3" q="3" result="and1"/>
    <playFT numDef="69" numOff="444" pos="away" q="3" throws="1" throwsMade="0"/>
    <play numDef="375" numOff="375" pos="home" pts="2" q="3" result="and1made"/>
    <play numDef="879" numOff="666" pos="away" pts="3" q="3" result="foul"/>
    <playFT numDef="420" numOff="311" pos="away" q="3" throws="3" throwsMade="3"/>
    <play numDef="609" numOff="640" pos="home" pts="2" q="3" result="made"/>
    <play numDef="640" numOff="222" pos="away" pts="3" q="3" result="turnover"/>
    <play numDef="333" numOff="777" pos="home" pts="2" q="3" result="turnover"/>
    <play numDef="611" numOff="904" pos="away" pts="3" q="3" result="miss"/>
    <play numDef="611" numOff="404" pos="home" pts="2" q="3" result="made"/>
    <play numDef="1" numOff="199" pos="away" pts="3" q="3" result="made"/>
    <play numDef="345" numOff="100" pos="home" pts="2" q="4" result="made"/>
    <play numDef="569" numOff="255" pos="away" pts="3" q="4" result="miss"/>
    <play numDef="920" numOff="750" pos="home" pts="2" q="4" result="made"/>
    <play numDef="404" numOff="799" pos="away" pts="3" q="4" result="miss"/>
    <play numDef="303" numOff="1000" pos="home" pts="2" q="4" result="made"/>
    <play numDef="650" numOff="420" offStrat="hurry" pos="away" pts="3" q="4" result="rebound"/>
    <play numDef="420" numOff="904" offStrat="hurry" pos="away" pts="3" q="4" result="dunk"/>
    <play numDef="777" numOff="199" offStrat="hurry" pos="away" pts="3" q="4" result="turnover"/>
    <play numDef="650" numOff="350" offStrat="chew" pos="home" pts="2" q="4" result="made"/>
    <play numDef="123" numOff="750" offStrat="hurry" pos="away" pts="3" q="4" result="miss"/>
    <play numDef="312" numOff="1000" offStrat="chew" pos="home" pts="2" q="4" result="foul"/>
    <playFT numDef="890" numOff="69" pos="home" q="4" throws="2" throwsMade="2"/>
    <play numDef="658" numOff="777" offStrat="hurry" pos="away" pts="3" q="4" result="made"/>
    <play numDef="404" numOff="444" offStrat="chew" pos="home" pts="2" q="4" result="made"/>
    <play numDef="999" numOff="1" offStrat="hurry" pos="away" pts="3" q="4" result="and1"/>
    <playFT numDef="569" numOff="888" pos="away" q="4" throws="1" throwsMade="1"/>
    <play numDef="950" numOff="777" offStrat="chew" pos="home" pts="2" q="4" result="made"/>
    <play numDef="777" numOff="199" offStrat="hurry" pos="away" pts="3" q="4" result="turnover"/>
    <play defStrat="foul" numDef="500" numOff="569" offStrat="chew" pos="home" pts="2" q="4" result="foul"/>
    <playFT numDef="888" numOff="310" pos="home" q="4" throws="2" throwsMade="1"/>
    <play numDef="810" numOff="420" offStrat="hurry" pos="away" pts="3" q="4" result="miss"/>
    <play defStrat="press" numDef="904" numOff="69" offStrat="chew" pos="home" pts="3" q="4" result="made"/>
    <play numDef="69" numOff="199" offStrat="hurry" pos="away" pts="3" q="4" result="made"/>
    <play defStrat="foul" numDef="569" numOff="69" pos="home" pts="3" q="4" result="dunk"/>
    <play defStrat="foul" numDef="920" numOff="69" pos="home" pts="hc" q="4" result="foul"/>
    <playFT numDef="569" numOff="250" pos="home" q="4" throws="2" throwsMade="1"/>
  </plays>
</game>
