<?xml version="1.0" encoding="UTF-8" standalone="no"?>
<game game-type="preseason" uuid="86f6e162055d435d95d73adab8f31860" version="2.1">
  <meta>
    <homeTeam>
      <team defStrat="MAN" discordId="203362581363032064" fullName="Huskies" id="washington" offStrat="ISO" shortName="Washington"/>
    </homeTeam>
    <awayTeam>
      <team defStrat="MAN" discordId="199065947795881984" fullName="Hawkeyes" id="iowa" offStrat="4-Out" shortName="Iowa"/>
    </awayTeam>
    <startTime>1607741900589</startTime>
    <gameTitle>Preseason Test 2</gameTitle>
    <channelName>uw-vs-iowa</channelName>
  </meta>
  <scores>
    <quarter away="66" home="51" q="F"/>
    <quarter away="20" home="11" q="1"/>
    <quarter away="19" home="20" q="2"/>
    <quarter away="17" home="10" q="3"/>
    <quarter away="10" home="10" q="4"/>
    <quarter away="0" home="0" q="O1"/>
  </scores>
  <plays>
    <tipoff away="319" home="550" tip="447"/>
    <play numDef="487" numOff="199" pos="away" pts="3" q="1" result="miss"/>
    <play numDef="1000" numOff="890" pos="home" pts="2" q="1" result="made"/>
    <play numDef="55" numOff="750" pos="away" pts="3" q="1" result="miss"/>
    <play numDef="399" numOff="567" pos="home" pts="2" q="1" result="made"/>
    <play numDef="648" numOff="206" pos="away" pts="3" q="1" result="turnover"/>
    <play numDef="500" numOff="234" pos="home" pts="2" q="1" result="made"/>
    <play numDef="744" numOff="808" pos="away" pts="3" q="1" result="made"/>
    <play numDef="689" numOff="118" pos="home" pts="2" q="1" result="turnover"/>
    <play numDef="12" numOff="350" pos="away" pts="3" q="1" result="miss"/>
    <play numDef="462" numOff="232" pos="home" pts="2" q="1" result="made"/>
    <play numDef="341" numOff="500" pos="away" pts="3" q="1" result="made"/>
    <play numDef="737" numOff="678" pos="home" pts="2" q="1" result="made"/>
    <play numDef="734" numOff="888" pos="away" pts="3" q="1" result="made"/>
    <play numDef="109" numOff="269" pos="home" pts="2" q="1" result="made"/>
    <play numDef="112" numOff="420" pos="away" pts="3" q="1" result="miss"/>
    <play numDef="920" numOff="903" pos="away" pts="3" q="1" result="and1"/>
    <playFT numDef="300" numOff="332" pos="away" q="1" throws="1" throwsMade="1"/>
    <play numDef="721" numOff="950" pos="home" pts="3" q="1" result="foul"/>
    <playFT numDef="72" numOff="750" pos="home" q="1" throws="3" throwsMade="2"/>
    <play numDef="316" numOff="231" pos="home" pts="2" q="1" result="made"/>
    <play numDef="845" numOff="400" pos="away" pts="3" q="1" result="turnover"/>
    <play numDef="808" numOff="767" offStrat="hurry" pos="home" pts="2" q="1" result="made"/>
    <play numDef="349" numOff="599" pos="home" pts="3" q="2" result="rebound"/>
    <play numDef="223" numOff="499" pos="away" pts="3" q="2" result="miss"/>
    <play numDef="999" numOff="520" pos="away" pts="2" q="2" result="dunk"/>
    <play numDef="333" numOff="243" pos="home" pts="3" q="2" result="made"/>
    <play numDef="232" numOff="420" pos="away" pts="3" q="2" result="made"/>
    <play numDef="1000" numOff="777" pos="away" pts="3" q="2" result="rebound"/>
    <play numDef="500" numOff="229" pos="home" pts="2" q="2" result="made"/>
    <play numDef="819" numOff="471" pos="away" pts="3" q="2" result="miss"/>
    <play numDef="808" numOff="567" pos="home" pts="2" q="2" result="made"/>
    <play numDef="456" numOff="462" pos="home" pts="3" q="2" result="and1"/>
    <playFT numDef="823" numOff="206" pos="home" q="2" throws="1" throwsMade="0"/>
    <play numDef="666" numOff="566" pos="home" pts="2" q="2" result="made"/>
    <play numDef="122" numOff="250" pos="away" pts="3" q="2" result="made"/>
    <play numDef="300" numOff="394" pos="home" pts="3" q="2" result="made"/>
    <play numDef="586" numOff="500" pos="away" pts="3" q="2" result="made"/>
    <play numDef="1" numOff="105" offStrat="chew" pos="home" pts="3" q="2" result="made"/>
    <play numDef="684" numOff="847" pos="away" pts="3" q="2" result="made"/>
    <play numDef="500" numOff="623" pos="home" pts="2" q="2" result="made"/>
    <play defStrat="press" numDef="784" numOff="316" pos="home" pts="3" q="2" result="dunk"/>
    <play numDef="962" numOff="10" offStrat="hurry" pos="away" pts="3" q="2" result="made"/>
    <play numDef="744" numOff="831" pos="home" pts="2" q="3" result="made"/>
    <play numDef="618" numOff="400" pos="home" pts="3" q="3" result="foul"/>
    <playFT numDef="81" numOff="500" pos="home" q="3" throws="3" throwsMade="1"/>
    <play numDef="6" numOff="652" pos="away" pts="2" q="3" result="rebound"/>
    <play numDef="800" numOff="567" pos="home" pts="2" q="3" result="made"/>
    <play numDef="810" numOff="354" pos="away" pts="3" q="3" result="turnover"/>
    <play numDef="205" numOff="410" pos="home" pts="2" q="3" result="made"/>
    <play numDef="985" numOff="650" pos="away" pts="3" q="3" result="miss"/>
    <play numDef="1" numOff="610" pos="home" pts="3" q="3" result="miss"/>
    <play numDef="891" numOff="439" pos="away" pts="3" q="3" result="turnover"/>
    <play numDef="789" numOff="38" pos="home" pts="2" q="3" result="made"/>
    <play numDef="512" numOff="267" pos="home" pts="3" q="3" result="rebound"/>
    <play numDef="672" numOff="300" pos="away" pts="3" q="3" result="miss"/>
    <play numDef="888" numOff="910" pos="home" pts="3" q="3" result="made"/>
    <play numDef="623" numOff="592" pos="away" pts="3" q="3" result="made"/>
    <play numDef="124" numOff="122" pos="away" pts="2" q="3" result="and1"/>
    <playFT numDef="234" numOff="335" pos="away" q="3" throws="1" throwsMade="1"/>
    <play numDef="711" numOff="900" pos="away" pts="3" q="3" result="made"/>
    <play numDef="333" numOff="19" pos="away" pts="2" q="3" result="foul"/>
    <playFT numDef="666" numOff="829" pos="away" q="3" throws="2" throwsMade="2"/>
    <play numDef="632" numOff="563" pos="away" pts="3" q="3" result="made"/>
    <play numDef="569" numOff="209" offStrat="chew" pos="away" pts="2" q="3" result="miss"/>
    <play numDef="920" numOff="444" pos="home" pts="3" q="4" result="dunk"/>
    <play numDef="722" numOff="170" pos="away" pts="3" q="4" result="turnover"/>
    <play numDef="808" numOff="103" offStrat="chew" pos="home" pts="2" q="4" result="made"/>
    <play numDef="310" numOff="350" pos="away" pts="3" q="4" result="made"/>
    <play numDef="787" numOff="349" offStrat="chew" pos="home" pts="2" q="4" result="turnover"/>
    <play numDef="980" numOff="562" offStrat="hurry" pos="away" pts="3" q="4" result="turnover"/>
    <play numDef="400" numOff="123" offStrat="chew" pos="home" pts="3" q="4" result="miss"/>
    <play numDef="821" numOff="1000" offStrat="hurry" pos="away" pts="3" q="4" result="made"/>
    <play numDef="469" numOff="121" offStrat="chew" pos="away" pts="2" q="4" result="rebound"/>
    <play numDef="448" numOff="622" offStrat="chew" pos="home" pts="2" q="4" result="made"/>
    <play numDef="442" numOff="789" pos="away" pts="3" q="4" result="miss"/>
    <play numDef="1" numOff="342" offStrat="chew" pos="away" pts="2" q="4" result="rebound"/>
    <play numDef="343" numOff="247" offStrat="chew" pos="home" pts="2" q="4" result="made"/>
    <play numDef="788" numOff="130" pos="away" pts="3" q="4" result="miss"/>
    <play numDef="500" numOff="560" offStrat="chew" pos="home" pts="2" q="4" result="made"/>
    <play numDef="853" numOff="700" offStrat="chew" pos="away" pts="3" q="4" result="made"/>
    <play numDef="1" numOff="1" offStrat="chew" pos="away" pts="2" q="4" result="and1made"/>
  </plays>
</game>
