<?xml version="1.0" encoding="UTF-8" standalone="no"?>
<game game-type="auto" terminated-early="0" uuid="b15a87d7a25344eeb017fd4a4f0eaa39" version="2.0">
  <meta>
    <homeTeam>
      <team defStrat="1-3-1" discordId="223980930975399937" fullName="Mr.Sir’s School for Gentlemen" id="223980930975399937" offStrat="5-Out" shortName="Gentlemen"/>
    </homeTeam>
    <awayTeam>
      <team defStrat="MAN" discordId="116109126832095239" fullName="Portland Tofurkey" id="116109126832095239" offStrat="4-Out" shortName="Tofurkey"/>
    </awayTeam>
    <startTime>1574026311453</startTime>
    <gameTitle>Portland Tofurkey @ Mr.Sir’s School for Gentlemen</gameTitle>
    <channelName>gentlemen-vs-tofurkey</channelName>
  </meta>
  <scores>
    <quarter away="57" home="40" q="F"/>
    <quarter away="11" home="10" q="1"/>
    <quarter away="14" home="11" q="2"/>
    <quarter away="15" home="12" q="3"/>
    <quarter away="17" home="7" q="4"/>
    <quarter away="0" home="0" q="O1"/>
  </scores>
  <plays>
    <tipoff away="12" home="443" tip="434"/>
    <play numDef="999" numOff="360" pos="home" pts="2" q="1" result="rebound"/>
    <play numDef="374" numOff="110" pos="away" pts="2" q="1" result="made"/>
    <play numDef="499" numOff="832" pos="away" pts="2" q="1" result="foul"/>
    <playFT numDef="808" numOff="400" pos="away" q="1" throws="2" throwsMade="1"/>
    <play numDef="927" numOff="330" pos="away" pts="2" q="1" result="miss"/>
    <play numDef="987" numOff="983" pos="away" pts="3" q="1" result="and1"/>
    <playFT numDef="299" numOff="837" pos="away" q="1" throws="1" throwsMade="0"/>
    <play numDef="98" numOff="110" pos="home" pts="2" q="1" result="and1"/>
    <playFT numDef="666" numOff="300" pos="home" q="1" throws="1" throwsMade="0"/>
    <play numDef="929" numOff="745" pos="home" pts="2" q="1" result="made"/>
    <play numDef="870" numOff="330" pos="away" pts="2" q="1" result="turnover"/>
    <play numDef="11" numOff="923" pos="home" pts="3" q="1" result="made"/>
    <play numDef="652" numOff="611" pos="away" pts="2" q="1" result="made"/>
    <play numDef="45" numOff="838" pos="home" pts="2" q="1" result="made"/>
    <play numDef="999" numOff="880" pos="away" pts="2" q="1" result="made"/>
    <play numDef="550" numOff="111" pos="home" pts="2" q="1" result="turnover"/>
    <play numDef="738" numOff="101" pos="home" pts="2" q="1" result="rebound"/>
    <play numDef="1000" numOff="101" offStrat="chew" pos="away" pts="2" q="1" result="made"/>
    <play numDef="1" numOff="827" pos="away" pts="3" q="1" result="made"/>
    <play numDef="738" numOff="750" pos="home" pts="2" q="2" result="and1"/>
    <playFT numDef="283" numOff="330" pos="home" q="2" throws="1" throwsMade="1"/>
    <play numDef="660" numOff="453" pos="home" pts="2" q="2" result="made"/>
    <play numDef="294" numOff="220" pos="away" pts="2" q="2" result="made"/>
    <play numDef="729" numOff="729" pos="home" pts="3" q="2" result="and1made"/>
    <play numDef="12" numOff="209" pos="away" pts="2" q="2" result="made"/>
    <play numDef="307" numOff="555" pos="home" pts="2" q="2" result="made"/>
    <play numDef="348" numOff="710" pos="home" pts="2" q="2" result="rebound"/>
    <play numDef="888" numOff="1" pos="away" pts="2" q="2" result="made"/>
    <play numDef="899" numOff="222" pos="away" pts="2" q="2" result="foul"/>
    <playFT numDef="275" numOff="12" pos="away" q="2" throws="2" throwsMade="1"/>
    <play numDef="872" numOff="200" pos="home" pts="2" q="2" result="foul"/>
    <playFT numDef="672" numOff="100" pos="home" q="2" throws="2" throwsMade="1"/>
    <play numDef="485" numOff="666" pos="home" pts="2" q="2" result="made"/>
    <play numDef="445" numOff="110" offStrat="hurry" pos="home" pts="2" q="2" result="foul"/>
    <playFT numDef="34" numOff="750" pos="home" q="2" throws="2" throwsMade="1"/>
    <play numDef="212" numOff="629" pos="home" pts="2" q="2" result="miss"/>
    <play numDef="892" numOff="440" offStrat="hurry" pos="away" pts="3" q="2" result="turnover"/>
    <play numDef="40" numOff="999" pos="home" pts="2" q="2" result="made"/>
    <play numDef="333" numOff="800" pos="away" pts="3" q="2" result="turnover"/>
    <play numDef="888" numOff="281" pos="home" pts="3" q="2" result="turnover"/>
    <play numDef="290" numOff="111" pos="home" pts="3" q="3" result="made"/>
    <play numDef="456" numOff="880" offStrat="hurry" pos="away" pts="2" q="3" result="miss"/>
    <play numDef="119" numOff="420" pos="home" pts="3" q="3" result="miss"/>
    <play numDef="800" numOff="110" offStrat="hurry" pos="away" pts="3" q="3" result="miss"/>
    <play numDef="797" numOff="683" pos="home" pts="3" q="3" result="made"/>
    <play numDef="672" numOff="699" pos="away" pts="3" q="3" result="made"/>
    <play numDef="42" numOff="888" pos="home" pts="2" q="3" result="made"/>
    <play numDef="23" numOff="299" offStrat="hurry" pos="away" pts="2" q="3" result="made"/>
    <play numDef="787" numOff="384" pos="home" pts="2" q="3" result="miss"/>
    <play numDef="837" numOff="119" pos="away" pts="2" q="3" result="made"/>
    <play numDef="5" numOff="333" pos="away" pts="2" q="3" result="foul"/>
    <playFT numDef="865" numOff="190" pos="away" q="3" throws="2" throwsMade="1"/>
    <play numDef="111" numOff="770" offStrat="hurry" pos="home" pts="2" q="3" result="rebound"/>
    <play numDef="681" numOff="110" offStrat="hurry" pos="away" pts="2" q="3" result="miss"/>
    <play numDef="989" numOff="892" pos="home" pts="3" q="3" result="made"/>
    <play numDef="380" numOff="220" offStrat="hurry" pos="away" pts="3" q="3" result="made"/>
    <play numDef="772" numOff="897" pos="home" pts="3" q="3" result="made"/>
    <play numDef="792" numOff="110" offStrat="hurry" pos="away" pts="3" q="3" result="miss"/>
    <play numDef="773" numOff="528" offStrat="hurry" pos="home" pts="3" q="3" result="miss"/>
    <play numDef="30" numOff="220" offStrat="hurry" pos="home" pts="3" q="3" result="foul"/>
    <playFT numDef="12" numOff="220" pos="home" q="3" throws="3" throwsMade="2"/>
    <play numDef="110" numOff="666" pos="home" pts="2" q="3" result="turnover"/>
    <play numDef="238" numOff="33" offStrat="hurry" pos="home" pts="3" q="4" result="foul"/>
    <playFT numDef="472" numOff="10" pos="home" q="4" throws="3" throwsMade="1"/>
    <play numDef="117" numOff="777" pos="home" pts="3" q="4" result="miss"/>
    <play numDef="666" numOff="550" offStrat="hurry" pos="away" pts="3" q="4" result="made"/>
    <play numDef="199" numOff="438" pos="home" pts="2" q="4" result="made"/>
    <play numDef="831" numOff="219" offStrat="hurry" pos="away" pts="2" q="4" result="miss"/>
    <play numDef="334" numOff="237" pos="home" pts="2" q="4" result="made"/>
    <play numDef="555" numOff="97" offStrat="hurry" pos="away" pts="3" q="4" result="turnover"/>
    <play numDef="97" numOff="223" pos="home" pts="2" q="4" result="made"/>
    <play numDef="892" numOff="110" offStrat="hurry" pos="home" pts="3" q="4" result="rebound"/>
    <play numDef="111" numOff="440" offStrat="hurry" pos="away" pts="3" q="4" result="miss"/>
    <play numDef="417" numOff="238" pos="home" pts="3" q="4" result="made"/>
    <play numDef="473" numOff="770" offStrat="hurry" pos="away" pts="3" q="4" result="miss"/>
    <play numDef="291" numOff="623" pos="away" pts="2" q="4" result="foul"/>
    <playFT numDef="192" numOff="111" pos="away" q="4" throws="2" throwsMade="2"/>
    <play numDef="444" numOff="12" offStrat="chew" pos="away" pts="2" q="4" result="turnover"/>
    <play numDef="120" numOff="527" pos="home" pts="2" q="4" result="miss"/>
    <play numDef="999" numOff="55" offStrat="chew" pos="away" pts="2" q="4" result="made"/>
    <play numDef="790" numOff="827" pos="home" pts="3" q="4" result="made"/>
    <play numDef="483" numOff="1" offStrat="chew" pos="home" pts="2" q="4" result="dunk"/>
    <play numDef="222" numOff="150" offStrat="chew" pos="home" pts="2" q="4" result="made"/>
  </plays>
</game>
